option_price_repair-0.3.0.dist-info/METADATA
option_price_repair-0.3.0.dist-info/WHEEL
option_price_repair-0.3.0.dist-info/entry_points.txt
option_price_repair-0.3.0.dist-info/licenses/LICENSE
option_price_repair/__init__.py
option_price_repair/analysis.py
option_price_repair/cvxpy.py
option_price_repair/repair.py
option_price_repair-0.3.0.dist-info/RECORD
