Metadata-Version: 2.4
Name: option-price-repair
Version: 0.3.0
Summary: Repair arbitrage in European call option prices.
Keywords: option,price,repair,finance,arbitrage,data,typing
Author: Christopher McDonald
License-Expression: MIT
License-File: LICENSE
Classifier: Development Status :: 4 - Beta
Classifier: Operating System :: OS Independent
Classifier: Intended Audience :: Developers
Classifier: Intended Audience :: Science/Research
Classifier: Intended Audience :: Financial and Insurance Industry
Classifier: Topic :: Office/Business :: Financial
Classifier: Topic :: Office/Business :: Financial :: Investment
Classifier: Topic :: Scientific/Engineering
Classifier: Programming Language :: Python
Classifier: Programming Language :: Python :: 3
Classifier: Programming Language :: Python :: 3 :: Only
Project-URL: Repository, http://github.com/chris-mcdo/option-price-repair
Requires-Python: >=3.9
Provides-Extra: analysis
Requires-Dist: plotly>=6.4.0; extra == "analysis"
Requires-Dist: polars>=1.35.2; extra == "analysis"
Provides-Extra: cvxpy
Requires-Dist: cvxpy>=1.7.3; extra == "cvxpy"
